taresamplers/__init__.py
taresamplers-0.0.1.dist-info/METADATA
taresamplers-0.0.1.dist-info/WHEEL
taresamplers-0.0.1.dist-info/licenses/LICENSE
taresamplers-0.0.1.dist-info/RECORD
