Metadata-Version: 2.3
Name: taresamplers
Version: 0.0.1
Summary: Utility wrapper for torchaudio resamplers.
Project-URL: Homepage, https://github.com/babua/torchaudio-resamplers
Project-URL: Issues, https://github.com/babua/torchaudio-resamplers/issues
Author-email: Onur Babacan <onurbabacan@gmail.com>
License-File: LICENSE
Classifier: License :: OSI Approved :: MIT License
Classifier: Operating System :: OS Independent
Classifier: Programming Language :: Python :: 3
Requires-Python: >=3.9
